object_bucket/__init__.py
object_bucket/core/__init__.py
object_bucket/core/bucket.py
object_bucket/core/bucket_funcs.py
object_bucket/errors/__init__.py
object_bucket/errors/bucket_error.py
object_bucket-1.6.1.dist-info/LICENSE
object_bucket-1.6.1.dist-info/METADATA
object_bucket-1.6.1.dist-info/WHEEL
object_bucket-1.6.1.dist-info/top_level.txt
object_bucket-1.6.1.dist-info/RECORD
