Metadata-Version: 2.1
Name: object-bucket
Version: 1.6.1
Summary: A fun and easy way to store python objects.
Home-page: https://github.com/Adwaith-Rajesh/object-bucket
Author: Adwaith-Rajesh
Author-email: adwaithrajesh3180@gmail.com
License: MIT
Platform: UNKNOWN
Classifier: License :: OSI Approved :: MIT License
Classifier: Programming Language :: Python :: 3
Classifier: Programming Language :: Python :: 3 :: Only
Classifier: Programming Language :: Python :: 3.6
Classifier: Programming Language :: Python :: 3.7
Classifier: Programming Language :: Python :: 3.8
Classifier: Programming Language :: Python :: 3.9
Requires-Python: >=3.6
Requires-Dist: dill (==0.3.4)
